[
  {
    "appName": "",
    "appNewVersion": "1.5.1095",
    "blockingProcesses": [],
    "downloadURL": "https://dl.wisprflow.com/wispr-flow/darwin/arm64/dmgs/Flow-v1.5.1095.dmg",
    "downloadURLi386": "https://dl.wisprflow.com/wispr-flow/darwin/x64/dmgs/Flow-v1.5.1095.dmg",
    "expectedTeamID": "C9VQZ78H85",
    "label": "wisprflow",
    "name": "Wispr Flow",
    "timeStamp": "2026-07-03T16:08:47Z",
    "type": "dmg"
  },
  {
    "appName": "",
    "appNewVersion": "1.6.7",
    "blockingProcesses": [],
    "downloadURL": "https://dl.wisprflow.com/wispr-flow/darwin/arm64/dmgs/Flow-v1.6.7.dmg",
    "downloadURLi386": "https://dl.wisprflow.com/wispr-flow/darwin/x64/dmgs/Flow-v1.6.7.dmg",
    "expectedTeamID": "C9VQZ78H85",
    "label": "wisprflow",
    "name": "Wispr Flow",
    "timeStamp": "2026-07-11T07:17:34Z",
    "type": "dmg"
  },
  {
    "appName": "",
    "appNewVersion": "1.6.224",
    "blockingProcesses": [],
    "downloadURL": "https://dl.wisprflow.com/wispr-flow/darwin/arm64/dmgs/Flow-v1.6.224.dmg",
    "downloadURLi386": "https://dl.wisprflow.com/wispr-flow/darwin/x64/dmgs/Flow-v1.6.224.dmg",
    "expectedTeamID": "C9VQZ78H85",
    "label": "wisprflow",
    "name": "Wispr Flow",
    "timeStamp": "2026-07-24T07:20:55Z",
    "type": "dmg"
  }
]
